{
    "version": "governance-index-1",
    "generated_at": "2026-01-31",
    "entries": [
        {
            "id": "gov-policies",
            "title": "Policies",
            "description": "Operational Lab policies and bounded governance references.",
            "href": "/policies",
            "scope": "public",
            "tier": "unified"
        },
        {
            "id": "gov-gates",
            "title": "Gates",
            "description": "Automated gate status and verification logic.",
            "href": "/gates",
            "scope": "public",
            "tier": "unified"
        },
        {
            "id": "gov-seals",
            "title": "Releases & Seals",
            "description": "Immutable release records and cryptographic seals.",
            "href": "/releases",
            "scope": "public",
            "tier": "unified"
        },
        {
            "id": "gov-audit",
            "title": "Audit",
            "description": "Local verification utilities and health checks.",
            "href": "/audit",
            "scope": "public",
            "tier": "unified"
        }
    ]
}
